colorist/__init__.py
colorist/py.typed
colorist/version.py
colorist/constants/__init__.py
colorist/constants/ansi.py
colorist/constants/ascii.py
colorist/helper/__init__.py
colorist/helper/convert.py
colorist/helper/error.py
colorist/helper/generate.py
colorist/helper/print.py
colorist/helper/validate.py
colorist/model/README.MD
colorist/model/__init__.py
colorist/model/effect.py
colorist/model/abc/color.py
colorist/model/abc/effect.py
colorist/model/abc/hex.py
colorist/model/abc/hsl.py
colorist/model/abc/mkdocstrings.py
colorist/model/abc/oklch.py
colorist/model/abc/rgb.py
colorist/model/abc/vga.py
colorist/model/background/__init__.py
colorist/model/background/bright_color.py
colorist/model/background/color.py
colorist/model/background/hex.py
colorist/model/background/hsl.py
colorist/model/background/oklch.py
colorist/model/background/rgb.py
colorist/model/background/vga.py
colorist/model/foreground/__init__.py
colorist/model/foreground/bright_color.py
colorist/model/foreground/color.py
colorist/model/foreground/hex.py
colorist/model/foreground/hsl.py
colorist/model/foreground/oklch.py
colorist/model/foreground/rgb.py
colorist/model/foreground/vga.py
colorist/print/__init__.py
colorist/print/effect.py
colorist/print/general.py
colorist/print/background/__init__.py
colorist/print/background/bright_color.py
colorist/print/background/color.py
colorist/print/background/hex.py
colorist/print/background/hsl.py
colorist/print/background/oklch.py
colorist/print/background/rgb.py
colorist/print/background/vga.py
colorist/print/foreground/__init__.py
colorist/print/foreground/bright_color.py
colorist/print/foreground/color.py
colorist/print/foreground/hex.py
colorist/print/foreground/hsl.py
colorist/print/foreground/oklch.py
colorist/print/foreground/rgb.py
colorist/print/foreground/vga.py
colorist/style/__init__.py
colorist/style/text.py
colorist-1.8.11.dist-info/licenses/LICENSE.md
colorist-1.8.11.dist-info/METADATA
colorist-1.8.11.dist-info/WHEEL
colorist-1.8.11.dist-info/top_level.txt
colorist-1.8.11.dist-info/RECORD
