Metadata-Version: 2.4
Name: colorist
Version: 1.8.11
Summary: Lightweight package that makes it easy and fast to print colored text in the terminal
Home-page: https://jakob-bagterp.github.io/colorist-for-python/
Download-URL: https://pypi.org/project/colorist/
Author: Jakob Bagterp
Author-email: jakob_bagterp@hotmail.com
Maintainer: Jakob Bagterp
Maintainer-email: jakob_bagterp@hotmail.com
License: 3-Clause BSD License
Project-URL: Bug Tracker, https://github.com/jakob-bagterp/colorist-for-python/issues
Project-URL: Documentation, https://jakob-bagterp.github.io/colorist-for-python/
Project-URL: API Reference, https://jakob-bagterp.github.io/colorist-for-python/reference/
Project-URL: Source Code, https://github.com/jakob-bagterp/colorist-for-python
Project-URL: Release Notes, https://github.com/jakob-bagterp/colorist-for-python/releases
Keywords: python,colors,terminal
Classifier: Programming Language :: Python :: 3
Classifier: Programming Language :: Python :: 3.10
Classifier: Programming Language :: Python :: 3.11
Classifier: Programming Language :: Python :: 3.12
Classifier: Programming Language :: Python :: 3.13
Classifier: Programming Language :: Python :: 3.14
Classifier: License :: OSI Approved :: BSD License
Classifier: Operating System :: OS Independent
Requires-Python: >=3.10
License-File: LICENSE.md
Provides-Extra: testing
Requires-Dist: coverage==7.13.1; extra == "testing"
Requires-Dist: flake8==7.3.0; extra == "testing"
Requires-Dist: mypy==1.19.1; extra == "testing"
Requires-Dist: pytest==9.0.2; extra == "testing"
Requires-Dist: pytest-cov==7.0.0; extra == "testing"
Requires-Dist: tox==4.32.0; extra == "testing"
Dynamic: download-url
Dynamic: license-file
